[{"Channel ID":"3711","Menu Name":"Joe Smith","Editor (User Name)":"kcraig","Section Name":"Joe Smith"},{"Channel ID":"3711","Menu Name":"Jason Jones","Editor (User Name)":"vcraig","Section Name":"Jason Jones"},{"Channel ID":"3711","Menu Name":"Rick Jones","Editor (User Name)":"scraig","Section Name":"Rick Jones"},{"Channel ID":"3711","Menu Name":"Jessica Rogers","Editor (User Name)":"vcraig","Section Name":"Jessica Rogers"},{"Channel ID":"3711","Menu Name":"Zachery Smith","Editor (User Name)":"scraig","Section Name":"Zachery Smith"},{"Channel ID":"3710","Menu Name":"Mathematics","Section Name":"Mathematics"},{"Channel ID":"3710","Menu Name":"Social Studies","Section Name":"Social Studies"},{"Channel ID":"3710","Menu Name":"Music","Section Name":"Music"},{"Channel ID":"3710","Menu Name":"Visual Arts","Section Name":"Visual Arts"}]